Workbook

Sheet Инструкция
A1: Учёт продаж: как пользоваться
A3: Цвета ячеек
A4: Жёлтые ячейки с синим текстом — их заполняете вы. Остальные считаются сами, их не трогайте.
A6: Порядок работы
A7: 1. «Товары» — внесите артикулы, названия, цены продажи, закупочные цены, начальный остаток и минимальный остаток.
A8: 2. «Клиенты» — внесите клиентов (название, контакты, реквизиты).
A9: 3. «Продажи» — на каждую проданную позицию одна строка: дата, № счёта, клиент и артикул (выбираются из списка), количество.
A10: Название, цена, сумма, себестоимость и прибыль подставятся автоматически.
A11: Если в счёте несколько товаров — несколько строк с одним и тем же № счёта.
A12: 4. «Приход» — записывайте поступления товара, остатки на листе «Товары» обновятся сами.
A13: 5. «Отчёт» — выручка и прибыль по месяцам, график, рейтинг товаров и клиентов. Год меняется в ячейке B2.
A14: 6. «Счёт» — введите номер счёта, и лист заполнится из «Продаж». Не забудьте вписать реквизиты поставщика в B7. Печать или PDF — как обычно.
... A25: Файл подходит и для Google Таблиц: загрузите его в Google Диск и откройте как таблицу.

Sheet Продажи
A1: Дата | B1: № счёта | C1: Клиент | D1: Артикул | E1: Название | F1: Кол-во | G1: Цена | H1: Сумма | I1: Себестоимость | J1: Прибыль | K1: Месяц | L1: Год | M1: Ключ строки
A2: 46034 | B2: 1001 | C2: ТОО «Альфа» | D2: A-001 | E2: =IF(D2="","",IFERROR(INDEX(Товары!$B$2:$B$200,MATCH(D2,Товары!$A$2:$A$200,0)),"нет в справочнике")) -> Товар 1 | F2: 10 | G2: =IF(D2="","",IFERROR(INDEX(Товары!$C$2:$C$200,MATCH(D2,Товары!$A$2:$A$200,0)),0)) -> 15000 | H2: =IF(D2="","",F2*G2) -> 150000 | I2: =IF(D2="","",F2*IFERROR(INDEX(Товары!$D$2:$D$200,MATCH(D2,Товары!$A$2:$A$200,0)),0)) -> 90000 | J2: =IF(D2="","",H2-I2) -> 60000 | K2: =IF(A2="","",MONTH(A2)) -> 1 | L2: =IF(A2="","",YEAR(A2)) -> 2026 | M2: =IF(B2="","",B2&"|"&COUNTIF(B$2:B2,B2)) -> 1001|1
A3: 46034 | B3: 1001 | C3: ТОО «Альфа» | D3: A-002 | E3: =IF(D3="","",IFERROR(INDEX(Товары!$B$2:$B$200,MATCH(D3,Товары!$A$2:$A$200,0)),"нет в справочнике")) -> Товар 2 | F3: 5 | G3: =IF(D3="","",IFERROR(INDEX(Товары!$C$2:$C$200,MATCH(D3,Товары!$A$2:$A$200,0)),0)) -> 8500 | H3: =IF(D3="","",F3*G3) -> 42500 | I3: =IF(D3="","",F3*IFERROR(INDEX(Товары!$D$2:$D$200,MATCH(D3,Товары!$A$2:$A$200,0)),0)) -> 25000 | J3: =IF(D3="","",H3-I3) -> 17500 | K3: =IF(A3="","",MONTH(A3)) -> 1 | L3: =IF(A3="","",YEAR(A3)) -> 2026 | M3: =IF(B3="","",B3&"|"&COUNTIF(B$2:B3,B3)) -> 1001|2
A4: 46056 | B4: 1002 | C4: ИП Нурланов | D4: A-003 | E4: =IF(D4="","",IFERROR(INDEX(Товары!$B$2:$B$200,MATCH(D4,Товары!$A$2:$A$200,0)),"нет в справочнике")) -> Товар 3 | F4: 20 | G4: =IF(D4="","",IFERROR(INDEX(Товары!$C$2:$C$200,MATCH(D4,Товары!$A$2:$A$200,0)),0)) -> 3200 | H4: =IF(D4="","",F4*G4) -> 64000 | I4: =IF(D4="","",F4*IFERROR(INDEX(Товары!$D$2:$D$200,MATCH(D4,Товары!$A$2:$A$200,0)),0)) -> 36000 | J4: =IF(D4="","",H4-I4) -> 28000 | K4: =IF(A4="","",MONTH(A4)) -> 2 | L4: =IF(A4="","",YEAR(A4)) -> 2026 | M4: =IF(B4="","",B4&"|"&COUNTIF(B$2:B4,B4)) -> 1002|1
A5: 46071 | B5: 1003 | C5: ТОО «Бета» | D5: A-001 | E5: =IF(D5="","",IFERROR(INDEX(Товары!$B$2:$B$200,MATCH(D5,Товары!$A$2:$A$200,0)),"нет в справочнике")) -> Товар 1 | F5: 4 | G5: =IF(D5="","",IFERROR(INDEX(Товары!$C$2:$C$200,MATCH(D5,Товары!$A$2:$A$200,0)),0)) -> 15000 | H5: =IF(D5="","",F5*G5) -> 60000 | I5: =IF(D5="","",F5*IFERROR(INDEX(Товары!$D$2:$D$200,MATCH(D5,Товары!$A$2:$A$200,0)),0)) -> 36000 | J5: =IF(D5="","",H5-I5) -> 24000 | K5: =IF(A5="","",MONTH(A5)) -> 2 | L5: =IF(A5="","",YEAR(A5)) -> 2026 | M5: =IF(B5="","",B5&"|"&COUNTIF(B$2:B5,B5)) -> 1003|1
A6: 46088 | B6: 1004 | C6: ИП Нурланов | D6: A-004 | E6: =IF(D6="","",IFERROR(INDEX(Товары!$B$2:$B$200,MATCH(D6,Товары!$A$2:$A$200,0)),"нет в справочнике")) -> Товар 4 | F6: 12 | G6: =IF(D6="","",IFERROR(INDEX(Товары!$C$2:$C$200,MATCH(D6,Товары!$A$2:$A$200,0)),0)) -> 25000 | H6: =IF(D6="","",F6*G6) -> 300000 | I6: =IF(D6="","",F6*IFERROR(INDEX(Товары!$D$2:$D$200,MATCH(D6,Товары!$A$2:$A$200,0)),0)) -> 192000 | J6: =IF(D6="","",H6-I6) -> 108000 | K6: =IF(A6="","",MONTH(A6)) -> 3 | L6: =IF(A6="","",YEAR(A6)) -> 2026 | M6: =IF(B6="","",B6&"|"&COUNTIF(B$2:B6,B6)) -> 1004|1
A7: 46133 | B7: 1005 | C7: ТОО «Альфа» | D7: A-002 | E7: =IF(D7="","",IFERROR(INDEX(Товары!$B$2:$B$200,MATCH(D7,Товары!$A$2:$A$200,0)),"нет в справочнике")) -> Товар 2 | F7: 8 | G7: =IF(D7="","",IFERROR(INDEX(Товары!$C$2:$C$200,MATCH(D7,Товары!$A$2:$A$200,0)),0)) -> 8500 | H7: =IF(D7="","",F7*G7) -> 68000 | I7: =IF(D7="","",F7*IFERROR(INDEX(Товары!$D$2:$D$200,MATCH(D7,Товары!$A$2:$A$200,0)),0)) -> 40000 | J7: =IF(D7="","",H7-I7) -> 28000 | K7: =IF(A7="","",MONTH(A7)) -> 4 | L7: =IF(A7="","",YEAR(A7)) -> 2026 | M7: =IF(B7="","",B7&"|"&COUNTIF(B$2:B7,B7)) -> 1005|1
A8: 46182 | B8: 1006 | C8: ТОО «Бета» | D8: A-003 | E8: =IF(D8="","",IFERROR(INDEX(Товары!$B$2:$B$200,MATCH(D8,Товары!$A$2:$A$200,0)),"нет в справочнике")) -> Товар 3 | F8: 30 | G8: =IF(D8="","",IFERROR(INDEX(Товары!$C$2:$C$200,MATCH(D8,Товары!$A$2:$A$200,0)),0)) -> 3200 | H8: =IF(D8="","",F8*G8) -> 96000 | I8: =IF(D8="","",F8*IFERROR(INDEX(Товары!$D$2:$D$200,MATCH(D8,Товары!$A$2:$A$200,0)),0)) -> 54000 | J8: =IF(D8="","",H8-I8) -> 42000 | K8: =IF(A8="","",MONTH(A8)) -> 6 | L8: =IF(A8="","",YEAR(A8)) -> 2026 | M8: =IF(B8="","",B8&"|"&COUNTIF(B$2:B8,B8)) -> 1006|1
A9: 46280 | B9: 1007 | C9: ИП Нурланов | D9: A-001 | E9: =IF(D9="","",IFERROR(INDEX(Товары!$B$2:$B$200,MATCH(D9,Товары!$A$2:$A$200,0)),"нет в справочнике")) -> Товар 1 | F9: 6 | G9: =IF(D9="","",IFERROR(INDEX(Товары!$C$2:$C$200,MATCH(D9,Товары!$A$2:$A$200,0)),0)) -> 15000 | H9: =IF(D9="","",F9*G9) -> 90000 | I9: =IF(D9="","",F9*IFERROR(INDEX(Товары!$D$2:$D$200,MATCH(D9,Товары!$A$2:$A$200,0)),0)) -> 54000 | J9: =IF(D9="","",H9-I9) -> 36000 | K9: =IF(A9="","",MONTH(A9)) -> 9 | L9: =IF(A9="","",YEAR(A9)) -> 2026 | M9: =IF(B9="","",B9&"|"&COUNTIF(B$2:B9,B9)) -> 1007|1
E10: =IF(D10="","",IFERROR(INDEX(Товары!$B$2:$B$200,MATCH(D10,Товары!$A$2:$A$200,0)),"нет в справочнике")) | G10: =IF(D10="","",IFERROR(INDEX(Товары!$C$2:$C$200,MATCH(D10,Товары!$A$2:$A$200,0)),0)) | H10: =IF(D10="","",F10*G10) | I10: =IF(D10="","",F10*IFERROR(INDEX(Товары!$D$2:$D$200,MATCH(D10,Товары!$A$2:$A$200,0)),0)) | J10: =IF(D10="","",H10-I10) | K10: =IF(A10="","",MONTH(A10)) | L10: =IF(A10="","",YEAR(A10)) | M10: =IF(B10="","",B10&"|"&COUNTIF(B$2:B10,B10))
E11: =IF(D11="","",IFERROR(INDEX(Товары!$B$2:$B$200,MATCH(D11,Товары!$A$2:$A$200,0)),"нет в справочнике")) | G11: =IF(D11="","",IFERROR(INDEX(Товары!$C$2:$C$200,MATCH(D11,Товары!$A$2:$A$200,0)),0)) | H11: =IF(D11="","",F11*G11) | I11: =IF(D11="","",F11*IFERROR(INDEX(Товары!$D$2:$D$200,MATCH(D11,Товары!$A$2:$A$200,0)),0)) | J11: =IF(D11="","",H11-I11) | K11: =IF(A11="","",MONTH(A11)) | L11: =IF(A11="","",YEAR(A11)) | M11: =IF(B11="","",B11&"|"&COUNTIF(B$2:B11,B11))
E12: =IF(D12="","",IFERROR(INDEX(Товары!$B$2:$B$200,MATCH(D12,Товары!$A$2:$A$200,0)),"нет в справочнике")) | G12: =IF(D12="","",IFERROR(INDEX(Товары!$C$2:$C$200,MATCH(D12,Товары!$A$2:$A$200,0)),0)) | H12: =IF(D12="","",F12*G12) | I12: =IF(D12="","",F12*IFERROR(INDEX(Товары!$D$2:$D$200,MATCH(D12,Товары!$A$2:$A$200,0)),0)) | J12: =IF(D12="","",H12-I12) | K12: =IF(A12="","",MONTH(A12)) | L12: =IF(A12="","",YEAR(A12)) | M12: =IF(B12="","",B12&"|"&COUNTIF(B$2:B12,B12))
E13: =IF(D13="","",IFERROR(INDEX(Товары!$B$2:$B$200,MATCH(D13,Товары!$A$2:$A$200,0)),"нет в справочнике")) | G13: =IF(D13="","",IFERROR(INDEX(Товары!$C$2:$C$200,MATCH(D13,Товары!$A$2:$A$200,0)),0)) | H13: =IF(D13="","",F13*G13) | I13: =IF(D13="","",F13*IFERROR(INDEX(Товары!$D$2:$D$200,MATCH(D13,Товары!$A$2:$A$200,0)),0)) | J13: =IF(D13="","",H13-I13) | K13: =IF(A13="","",MONTH(A13)) | L13: =IF(A13="","",YEAR(A13)) | M13: =IF(B13="","",B13&"|"&COUNTIF(B$2:B13,B13))
E14: =IF(D14="","",IFERROR(INDEX(Товары!$B$2:$B$200,MATCH(D14,Товары!$A$2:$A$200,0)),"нет в справочнике")) | G14: =IF(D14="","",IFERROR(INDEX(Товары!$C$2:$C$200,MATCH(D14,Товары!$A$2:$A$200,0)),0)) | H14: =IF(D14="","",F14*G14) | I14: =IF(D14="","",F14*IFERROR(INDEX(Товары!$D$2:$D$200,MATCH(D14,Товары!$A$2:$A$200,0)),0)) | J14: =IF(D14="","",H14-I14) | K14: =IF(A14="","",MONTH(A14)) | L14: =IF(A14="","",YEAR(A14)) | M14: =IF(B14="","",B14&"|"&COUNTIF(B$2:B14,B14))
E15: =IF(D15="","",IFERROR(INDEX(Товары!$B$2:$B$200,MATCH(D15,Товары!$A$2:$A$200,0)),"нет в справочнике")) | G15: =IF(D15="","",IFERROR(INDEX(Товары!$C$2:$C$200,MATCH(D15,Товары!$A$2:$A$200,0)),0)) | H15: =IF(D15="","",F15*G15) | I15: =IF(D15="","",F15*IFERROR(INDEX(Товары!$D$2:$D$200,MATCH(D15,Товары!$A$2:$A$200,0)),0)) | J15: =IF(D15="","",H15-I15) | K15: =IF(A15="","",MONTH(A15)) | L15: =IF(A15="","",YEAR(A15)) | M15: =IF(B15="","",B15&"|"&COUNTIF(B$2:B15,B15))
E16: =IF(D16="","",IFERROR(INDEX(Товары!$B$2:$B$200,MATCH(D16,Товары!$A$2:$A$200,0)),"нет в справочнике")) | G16: =IF(D16="","",IFERROR(INDEX(Товары!$C$2:$C$200,MATCH(D16,Товары!$A$2:$A$200,0)),0)) | H16: =IF(D16="","",F16*G16) | I16: =IF(D16="","",F16*IFERROR(INDEX(Товары!$D$2:$D$200,MATCH(D16,Товары!$A$2:$A$200,0)),0)) | J16: =IF(D16="","",H16-I16) | K16: =IF(A16="","",MONTH(A16)) | L16: =IF(A16="","",YEAR(A16)) | M16: =IF(B16="","",B16&"|"&COUNTIF(B$2:B16,B16))
E17: =IF(D17="","",IFERROR(INDEX(Товары!$B$2:$B$200,MATCH(D17,Товары!$A$2:$A$200,0)),"нет в справочнике")) | G17: =IF(D17="","",IFERROR(INDEX(Товары!$C$2:$C$200,MATCH(D17,Товары!$A$2:$A$200,0)),0)) | H17: =IF(D17="","",F17*G17) | I17: =IF(D17="","",F17*IFERROR(INDEX(Товары!$D$2:$D$200,MATCH(D17,Товары!$A$2:$A$200,0)),0)) | J17: =IF(D17="","",H17-I17) | K17: =IF(A17="","",MONTH(A17)) | L17: =IF(A17="","",YEAR(A17)) | M17: =IF(B17="","",B17&"|"&COUNTIF(B$2:B17,B17))
E18: =IF(D18="","",IFERROR(INDEX(Товары!$B$2:$B$200,MATCH(D18,Товары!$A$2:$A$200,0)),"нет в справочнике")) | G18: =IF(D18="","",IFERROR(INDEX(Товары!$C$2:$C$200,MATCH(D18,Товары!$A$2:$A$200,0)),0)) | H18: =IF(D18="","",F18*G18) | I18: =IF(D18="","",F18*IFERROR(INDEX(Товары!$D$2:$D$200,MATCH(D18,Товары!$A$2:$A$200,0)),0)) | J18: =IF(D18="","",H18-I18) | K18: =IF(A18="","",MONTH(A18)) | L18: =IF(A18="","",YEAR(A18)) | M18: =IF(B18="","",B18&"|"&COUNTIF(B$2:B18,B18))
E19: =IF(D19="","",IFERROR(INDEX(Товары!$B$2:$B$200,MATCH(D19,Товары!$A$2:$A$200,0)),"нет в справочнике")) | G19: =IF(D19="","",IFERROR(INDEX(Товары!$C$2:$C$200,MATCH(D19,Товары!$A$2:$A$200,0)),0)) | H19: =IF(D19="","",F19*G19) | I19: =IF(D19="","",F19*IFERROR(INDEX(Товары!$D$2:$D$200,MATCH(D19,Товары!$A$2:$A$200,0)),0)) | J19: =IF(D19="","",H19-I19) | K19: =IF(A19="","",MONTH(A19)) | L19: =IF(A19="","",YEAR(A19)) | M19: =IF(B19="","",B19&"|"&COUNTIF(B$2:B19,B19))
E20: =IF(D20="","",IFERROR(INDEX(Товары!$B$2:$B$200,MATCH(D20,Товары!$A$2:$A$200,0)),"нет в справочнике")) | G20: =IF(D20="","",IFERROR(INDEX(Товары!$C$2:$C$200,MATCH(D20,Товары!$A$2:$A$200,0)),0)) | H20: =IF(D20="","",F20*G20) | I20: =IF(D20="","",F20*IFERROR(INDEX(Товары!$D$2:$D$200,MATCH(D20,Товары!$A$2:$A$200,0)),0)) | J20: =IF(D20="","",H20-I20) | K20: =IF(A20="","",MONTH(A20)) | L20: =IF(A20="","",YEAR(A20)) | M20: =IF(B20="","",B20&"|"&COUNTIF(B$2:B20,B20))
E21: =IF(D21="","",IFERROR(INDEX(Товары!$B$2:$B$200,MATCH(D21,Товары!$A$2:$A$200,0)),"нет в справочнике")) | G21: =IF(D21="","",IFERROR(INDEX(Товары!$C$2:$C$200,MATCH(D21,Товары!$A$2:$A$200,0)),0)) | H21: =IF(D21="","",F21*G21) | I21: =IF(D21="","",F21*IFERROR(INDEX(Товары!$D$2:$D$200,MATCH(D21,Товары!$A$2:$A$200,0)),0)) | J21: =IF(D21="","",H21-I21) | K21: =IF(A21="","",MONTH(A21)) | L21: =IF(A21="","",YEAR(A21)) | M21: =IF(B21="","",B21&"|"&COUNTIF(B$2:B21,B21))
... E1000: =IF(D1000="","",IFERROR(INDEX(Товары!$B$2:$B$200,MATCH(D1000,Товары!$A$2:$A$200,0)),"нет в справочнике")) | G1000: =IF(D1000="","",IFERROR(INDEX(Товары!$C$2:$C$200,MATCH(D1000,Товары!$A$2:$A$200,0)),0)) | H1000: =IF(D1000="","",F1000*G1000) | I1000: =IF(D1000="","",F1000*IFERROR(INDEX(Товары!$D$2:$D$200,MATCH(D1000,Товары!$A$2:$A$200,0)),0)) | J1000: =IF(D1000="","",H1000-I1000) | K1000: =IF(A1000="","",MONTH(A1000)) | L1000: =IF(A1000="","",YEAR(A1000)) | M1000: =IF(B1000="","",B1000&"|"&COUNTIF(B$2:B1000,B1000))

Sheet Товары
A1: Артикул | B1: Название | C1: Цена продажи | D1: Закупочная цена | E1: Начальный остаток | F1: Приход | G1: Продано | H1: Остаток | I1: Мин. остаток | J1: Статус
A2: A-001 | B2: Товар 1 | C2: 15000 | D2: 9000 | E2: 50 | F2: =IF(A2="","",SUMIFS(Приход!$C$2:$C$1000,Приход!$B$2:$B$1000,A2)) -> 20 | G2: =IF(A2="","",SUMIFS(Продажи!$F$2:$F$1000,Продажи!$D$2:$D$1000,A2)) -> 20 | H2: =IF(A2="","",E2+F2-G2) -> 50 | I2: 10 | J2: =IF(A2="","",IF(H2<=I2,"Заказать","ОК")) -> ОК
A3: A-002 | B3: Товар 2 | C3: 8500 | D3: 5000 | E3: 30 | F3: =IF(A3="","",SUMIFS(Приход!$C$2:$C$1000,Приход!$B$2:$B$1000,A3)) -> 0 | G3: =IF(A3="","",SUMIFS(Продажи!$F$2:$F$1000,Продажи!$D$2:$D$1000,A3)) -> 13 | H3: =IF(A3="","",E3+F3-G3) -> 17 | I3: 8 | J3: =IF(A3="","",IF(H3<=I3,"Заказать","ОК")) -> ОК
A4: A-003 | B4: Товар 3 | C4: 3200 | D4: 1800 | E4: 100 | F4: =IF(A4="","",SUMIFS(Приход!$C$2:$C$1000,Приход!$B$2:$B$1000,A4)) -> 60 | G4: =IF(A4="","",SUMIFS(Продажи!$F$2:$F$1000,Продажи!$D$2:$D$1000,A4)) -> 50 | H4: =IF(A4="","",E4+F4-G4) -> 110 | I4: 40 | J4: =IF(A4="","",IF(H4<=I4,"Заказать","ОК")) -> ОК
A5: A-004 | B5: Товар 4 | C5: 25000 | D5: 16000 | E5: 20 | F5: =IF(A5="","",SUMIFS(Приход!$C$2:$C$1000,Приход!$B$2:$B$1000,A5)) -> 10 | G5: =IF(A5="","",SUMIFS(Продажи!$F$2:$F$1000,Продажи!$D$2:$D$1000,A5)) -> 12 | H5: =IF(A5="","",E5+F5-G5) -> 18 | I5: 5 | J5: =IF(A5="","",IF(H5<=I5,"Заказать","ОК")) -> ОК
F6: =IF(A6="","",SUMIFS(Приход!$C$2:$C$1000,Приход!$B$2:$B$1000,A6)) | G6: =IF(A6="","",SUMIFS(Продажи!$F$2:$F$1000,Продажи!$D$2:$D$1000,A6)) | H6: =IF(A6="","",E6+F6-G6) | J6: =IF(A6="","",IF(H6<=I6,"Заказать","ОК"))
F7: =IF(A7="","",SUMIFS(Приход!$C$2:$C$1000,Приход!$B$2:$B$1000,A7)) | G7: =IF(A7="","",SUMIFS(Продажи!$F$2:$F$1000,Продажи!$D$2:$D$1000,A7)) | H7: =IF(A7="","",E7+F7-G7) | J7: =IF(A7="","",IF(H7<=I7,"Заказать","ОК"))
F8: =IF(A8="","",SUMIFS(Приход!$C$2:$C$1000,Приход!$B$2:$B$1000,A8)) | G8: =IF(A8="","",SUMIFS(Продажи!$F$2:$F$1000,Продажи!$D$2:$D$1000,A8)) | H8: =IF(A8="","",E8+F8-G8) | J8: =IF(A8="","",IF(H8<=I8,"Заказать","ОК"))
F9: =IF(A9="","",SUMIFS(Приход!$C$2:$C$1000,Приход!$B$2:$B$1000,A9)) | G9: =IF(A9="","",SUMIFS(Продажи!$F$2:$F$1000,Продажи!$D$2:$D$1000,A9)) | H9: =IF(A9="","",E9+F9-G9) | J9: =IF(A9="","",IF(H9<=I9,"Заказать","ОК"))
F10: =IF(A10="","",SUMIFS(Приход!$C$2:$C$1000,Приход!$B$2:$B$1000,A10)) | G10: =IF(A10="","",SUMIFS(Продажи!$F$2:$F$1000,Продажи!$D$2:$D$1000,A10)) | H10: =IF(A10="","",E10+F10-G10) | J10: =IF(A10="","",IF(H10<=I10,"Заказать","ОК"))
F11: =IF(A11="","",SUMIFS(Приход!$C$2:$C$1000,Приход!$B$2:$B$1000,A11)) | G11: =IF(A11="","",SUMIFS(Продажи!$F$2:$F$1000,Продажи!$D$2:$D$1000,A11)) | H11: =IF(A11="","",E11+F11-G11) | J11: =IF(A11="","",IF(H11<=I11,"Заказать","ОК"))
F12: =IF(A12="","",SUMIFS(Приход!$C$2:$C$1000,Приход!$B$2:$B$1000,A12)) | G12: =IF(A12="","",SUMIFS(Продажи!$F$2:$F$1000,Продажи!$D$2:$D$1000,A12)) | H12: =IF(A12="","",E12+F12-G12) | J12: =IF(A12="","",IF(H12<=I12,"Заказать","ОК"))
F13: =IF(A13="","",SUMIFS(Приход!$C$2:$C$1000,Приход!$B$2:$B$1000,A13)) | G13: =IF(A13="","",SUMIFS(Продажи!$F$2:$F$1000,Продажи!$D$2:$D$1000,A13)) | H13: =IF(A13="","",E13+F13-G13) | J13: =IF(A13="","",IF(H13<=I13,"Заказать","ОК"))
F14: =IF(A14="","",SUMIFS(Приход!$C$2:$C$1000,Приход!$B$2:$B$1000,A14)) | G14: =IF(A14="","",SUMIFS(Продажи!$F$2:$F$1000,Продажи!$D$2:$D$1000,A14)) | H14: =IF(A14="","",E14+F14-G14) | J14: =IF(A14="","",IF(H14<=I14,"Заказать","ОК"))
F15: =IF(A15="","",SUMIFS(Приход!$C$2:$C$1000,Приход!$B$2:$B$1000,A15)) | G15: =IF(A15="","",SUMIFS(Продажи!$F$2:$F$1000,Продажи!$D$2:$D$1000,A15)) | H15: =IF(A15="","",E15+F15-G15) | J15: =IF(A15="","",IF(H15<=I15,"Заказать","ОК"))
F16: =IF(A16="","",SUMIFS(Приход!$C$2:$C$1000,Приход!$B$2:$B$1000,A16)) | G16: =IF(A16="","",SUMIFS(Продажи!$F$2:$F$1000,Продажи!$D$2:$D$1000,A16)) | H16: =IF(A16="","",E16+F16-G16) | J16: =IF(A16="","",IF(H16<=I16,"Заказать","ОК"))
F17: =IF(A17="","",SUMIFS(Приход!$C$2:$C$1000,Приход!$B$2:$B$1000,A17)) | G17: =IF(A17="","",SUMIFS(Продажи!$F$2:$F$1000,Продажи!$D$2:$D$1000,A17)) | H17: =IF(A17="","",E17+F17-G17) | J17: =IF(A17="","",IF(H17<=I17,"Заказать","ОК"))
... F200: =IF(A200="","",SUMIFS(Приход!$C$2:$C$1000,Приход!$B$2:$B$1000,A200)) | G200: =IF(A200="","",SUMIFS(Продажи!$F$2:$F$1000,Продажи!$D$2:$D$1000,A200)) | H200: =IF(A200="","",E200+F200-G200) | J200: =IF(A200="","",IF(H200<=I200,"Заказать","ОК"))

Sheet Приход
A1: Дата | B1: Артикул | C1: Кол-во | D1: Поставщик / комментарий
A2: 46027 | B2: A-001 | C2: 20 | D2: Поставщик 1
A3: 46082 | B3: A-004 | C3: 10 | D3: Поставщик 2
A4: 46157 | B4: A-003 | C4: 60 | D4: Поставщик 1

Sheet Клиенты
A1: Клиент | B1: Телефон | C1: Email | D1: Реквизиты / адрес | E1: Сумма покупок | F1: Последняя покупка
A2: ТОО «Альфа» | B2: +7 700 000 00 01 | C2: alpha@example.kz | D2: г. Астана, ул. Примерная 1, БИН 000000000001 | E2: =IF(A2="","",SUMIFS(Продажи!$H$2:$H$1000,Продажи!$C$2:$C$1000,A2)) -> 260500 | F2: =IF(A2="","",IF(COUNTIF(Продажи!$C$2:$C$1000,A2)=0,"",_xlfn.MAXIFS(Продажи!$A$2:$A$1000,Продажи!$C$2:$C$1000,A2))) -> 46133
A3: ТОО «Бета» | B3: +7 700 000 00 02 | C3: beta@example.kz | D3: г. Астана, ул. Примерная 2, БИН 000000000002 | E3: =IF(A3="","",SUMIFS(Продажи!$H$2:$H$1000,Продажи!$C$2:$C$1000,A3)) -> 156000 | F3: =IF(A3="","",IF(COUNTIF(Продажи!$C$2:$C$1000,A3)=0,"",_xlfn.MAXIFS(Продажи!$A$2:$A$1000,Продажи!$C$2:$C$1000,A3))) -> 46182
A4: ИП Нурланов | B4: +7 700 000 00 03 | C4: nurlanov@example.kz | D4: г. Астана, ул. Примерная 3, ИИН 000000000003 | E4: =IF(A4="","",SUMIFS(Продажи!$H$2:$H$1000,Продажи!$C$2:$C$1000,A4)) -> 454000 | F4: =IF(A4="","",IF(COUNTIF(Продажи!$C$2:$C$1000,A4)=0,"",_xlfn.MAXIFS(Продажи!$A$2:$A$1000,Продажи!$C$2:$C$1000,A4))) -> 46280
E5: =IF(A5="","",SUMIFS(Продажи!$H$2:$H$1000,Продажи!$C$2:$C$1000,A5)) | F5: =IF(A5="","",IF(COUNTIF(Продажи!$C$2:$C$1000,A5)=0,"",_xlfn.MAXIFS(Продажи!$A$2:$A$1000,Продажи!$C$2:$C$1000,A5)))
E6: =IF(A6="","",SUMIFS(Продажи!$H$2:$H$1000,Продажи!$C$2:$C$1000,A6)) | F6: =IF(A6="","",IF(COUNTIF(Продажи!$C$2:$C$1000,A6)=0,"",_xlfn.MAXIFS(Продажи!$A$2:$A$1000,Продажи!$C$2:$C$1000,A6)))
E7: =IF(A7="","",SUMIFS(Продажи!$H$2:$H$1000,Продажи!$C$2:$C$1000,A7)) | F7: =IF(A7="","",IF(COUNTIF(Продажи!$C$2:$C$1000,A7)=0,"",_xlfn.MAXIFS(Продажи!$A$2:$A$1000,Продажи!$C$2:$C$1000,A7)))
E8: =IF(A8="","",SUMIFS(Продажи!$H$2:$H$1000,Продажи!$C$2:$C$1000,A8)) | F8: =IF(A8="","",IF(COUNTIF(Продажи!$C$2:$C$1000,A8)=0,"",_xlfn.MAXIFS(Продажи!$A$2:$A$1000,Продажи!$C$2:$C$1000,A8)))
E9: =IF(A9="","",SUMIFS(Продажи!$H$2:$H$1000,Продажи!$C$2:$C$1000,A9)) | F9: =IF(A9="","",IF(COUNTIF(Продажи!$C$2:$C$1000,A9)=0,"",_xlfn.MAXIFS(Продажи!$A$2:$A$1000,Продажи!$C$2:$C$1000,A9)))
E10: =IF(A10="","",SUMIFS(Продажи!$H$2:$H$1000,Продажи!$C$2:$C$1000,A10)) | F10: =IF(A10="","",IF(COUNTIF(Продажи!$C$2:$C$1000,A10)=0,"",_xlfn.MAXIFS(Продажи!$A$2:$A$1000,Продажи!$C$2:$C$1000,A10)))
E11: =IF(A11="","",SUMIFS(Продажи!$H$2:$H$1000,Продажи!$C$2:$C$1000,A11)) | F11: =IF(A11="","",IF(COUNTIF(Продажи!$C$2:$C$1000,A11)=0,"",_xlfn.MAXIFS(Продажи!$A$2:$A$1000,Продажи!$C$2:$C$1000,A11)))
E12: =IF(A12="","",SUMIFS(Продажи!$H$2:$H$1000,Продажи!$C$2:$C$1000,A12)) | F12: =IF(A12="","",IF(COUNTIF(Продажи!$C$2:$C$1000,A12)=0,"",_xlfn.MAXIFS(Продажи!$A$2:$A$1000,Продажи!$C$2:$C$1000,A12)))
E13: =IF(A13="","",SUMIFS(Продажи!$H$2:$H$1000,Продажи!$C$2:$C$1000,A13)) | F13: =IF(A13="","",IF(COUNTIF(Продажи!$C$2:$C$1000,A13)=0,"",_xlfn.MAXIFS(Продажи!$A$2:$A$1000,Продажи!$C$2:$C$1000,A13)))
E14: =IF(A14="","",SUMIFS(Продажи!$H$2:$H$1000,Продажи!$C$2:$C$1000,A14)) | F14: =IF(A14="","",IF(COUNTIF(Продажи!$C$2:$C$1000,A14)=0,"",_xlfn.MAXIFS(Продажи!$A$2:$A$1000,Продажи!$C$2:$C$1000,A14)))
E15: =IF(A15="","",SUMIFS(Продажи!$H$2:$H$1000,Продажи!$C$2:$C$1000,A15)) | F15: =IF(A15="","",IF(COUNTIF(Продажи!$C$2:$C$1000,A15)=0,"",_xlfn.MAXIFS(Продажи!$A$2:$A$1000,Продажи!$C$2:$C$1000,A15)))
E16: =IF(A16="","",SUMIFS(Продажи!$H$2:$H$1000,Продажи!$C$2:$C$1000,A16)) | F16: =IF(A16="","",IF(COUNTIF(Продажи!$C$2:$C$1000,A16)=0,"",_xlfn.MAXIFS(Продажи!$A$2:$A$1000,Продажи!$C$2:$C$1000,A16)))
... E200: =IF(A200="","",SUMIFS(Продажи!$H$2:$H$1000,Продажи!$C$2:$C$1000,A200)) | F200: =IF(A200="","",IF(COUNTIF(Продажи!$C$2:$C$1000,A200)=0,"",_xlfn.MAXIFS(Продажи!$A$2:$A$1000,Продажи!$C$2:$C$1000,A200)))

Sheet Отчет
A1: Отчёт по продажам
A2: Год: | B2: 2026 | C2: ← поменяйте год, отчёт пересчитается
A4: Месяц | B4: Выручка | C4: Прибыль | D4: Позиций продано | E4: Маржа
A5: Январь | B5: =SUMIFS(Продажи!$H$2:$H$1000,Продажи!$L$2:$L$1000,$B$2,Продажи!$K$2:$K$1000,1) -> 192500 | C5: =SUMIFS(Продажи!$J$2:$J$1000,Продажи!$L$2:$L$1000,$B$2,Продажи!$K$2:$K$1000,1) -> 77500 | D5: =COUNTIFS(Продажи!$L$2:$L$1000,$B$2,Продажи!$K$2:$K$1000,1) -> 2 | E5: =IF(B5=0,0,C5/B5) -> 0.4025974
A6: Февраль | B6: =SUMIFS(Продажи!$H$2:$H$1000,Продажи!$L$2:$L$1000,$B$2,Продажи!$K$2:$K$1000,2) -> 124000 | C6: =SUMIFS(Продажи!$J$2:$J$1000,Продажи!$L$2:$L$1000,$B$2,Продажи!$K$2:$K$1000,2) -> 52000 | D6: =COUNTIFS(Продажи!$L$2:$L$1000,$B$2,Продажи!$K$2:$K$1000,2) -> 2 | E6: =IF(B6=0,0,C6/B6) -> 0.41935484
A7: Март | B7: =SUMIFS(Продажи!$H$2:$H$1000,Продажи!$L$2:$L$1000,$B$2,Продажи!$K$2:$K$1000,3) -> 300000 | C7: =SUMIFS(Продажи!$J$2:$J$1000,Продажи!$L$2:$L$1000,$B$2,Продажи!$K$2:$K$1000,3) -> 108000 | D7: =COUNTIFS(Продажи!$L$2:$L$1000,$B$2,Продажи!$K$2:$K$1000,3) -> 1 | E7: =IF(B7=0,0,C7/B7) -> 0.36
A8: Апрель | B8: =SUMIFS(Продажи!$H$2:$H$1000,Продажи!$L$2:$L$1000,$B$2,Продажи!$K$2:$K$1000,4) -> 68000 | C8: =SUMIFS(Продажи!$J$2:$J$1000,Продажи!$L$2:$L$1000,$B$2,Продажи!$K$2:$K$1000,4) -> 28000 | D8: =COUNTIFS(Продажи!$L$2:$L$1000,$B$2,Продажи!$K$2:$K$1000,4) -> 1 | E8: =IF(B8=0,0,C8/B8) -> 0.41176471
A9: Май | B9: =SUMIFS(Продажи!$H$2:$H$1000,Продажи!$L$2:$L$1000,$B$2,Продажи!$K$2:$K$1000,5) -> 0 | C9: =SUMIFS(Продажи!$J$2:$J$1000,Продажи!$L$2:$L$1000,$B$2,Продажи!$K$2:$K$1000,5) -> 0 | D9: =COUNTIFS(Продажи!$L$2:$L$1000,$B$2,Продажи!$K$2:$K$1000,5) -> 0 | E9: =IF(B9=0,0,C9/B9) -> 0
A10: Июнь | B10: =SUMIFS(Продажи!$H$2:$H$1000,Продажи!$L$2:$L$1000,$B$2,Продажи!$K$2:$K$1000,6) -> 96000 | C10: =SUMIFS(Продажи!$J$2:$J$1000,Продажи!$L$2:$L$1000,$B$2,Продажи!$K$2:$K$1000,6) -> 42000 | D10: =COUNTIFS(Продажи!$L$2:$L$1000,$B$2,Продажи!$K$2:$K$1000,6) -> 1 | E10: =IF(B10=0,0,C10/B10) -> 0.4375
A11: Июль | B11: =SUMIFS(Продажи!$H$2:$H$1000,Продажи!$L$2:$L$1000,$B$2,Продажи!$K$2:$K$1000,7) -> 0 | C11: =SUMIFS(Продажи!$J$2:$J$1000,Продажи!$L$2:$L$1000,$B$2,Продажи!$K$2:$K$1000,7) -> 0 | D11: =COUNTIFS(Продажи!$L$2:$L$1000,$B$2,Продажи!$K$2:$K$1000,7) -> 0 | E11: =IF(B11=0,0,C11/B11) -> 0
A12: Август | B12: =SUMIFS(Продажи!$H$2:$H$1000,Продажи!$L$2:$L$1000,$B$2,Продажи!$K$2:$K$1000,8) -> 0 | C12: =SUMIFS(Продажи!$J$2:$J$1000,Продажи!$L$2:$L$1000,$B$2,Продажи!$K$2:$K$1000,8) -> 0 | D12: =COUNTIFS(Продажи!$L$2:$L$1000,$B$2,Продажи!$K$2:$K$1000,8) -> 0 | E12: =IF(B12=0,0,C12/B12) -> 0
A13: Сентябрь | B13: =SUMIFS(Продажи!$H$2:$H$1000,Продажи!$L$2:$L$1000,$B$2,Продажи!$K$2:$K$1000,9) -> 90000 | C13: =SUMIFS(Продажи!$J$2:$J$1000,Продажи!$L$2:$L$1000,$B$2,Продажи!$K$2:$K$1000,9) -> 36000 | D13: =COUNTIFS(Продажи!$L$2:$L$1000,$B$2,Продажи!$K$2:$K$1000,9) -> 1 | E13: =IF(B13=0,0,C13/B13) -> 0.4
A14: Октябрь | B14: =SUMIFS(Продажи!$H$2:$H$1000,Продажи!$L$2:$L$1000,$B$2,Продажи!$K$2:$K$1000,10) -> 0 | C14: =SUMIFS(Продажи!$J$2:$J$1000,Продажи!$L$2:$L$1000,$B$2,Продажи!$K$2:$K$1000,10) -> 0 | D14: =COUNTIFS(Продажи!$L$2:$L$1000,$B$2,Продажи!$K$2:$K$1000,10) -> 0 | E14: =IF(B14=0,0,C14/B14) -> 0
A15: Ноябрь | B15: =SUMIFS(Продажи!$H$2:$H$1000,Продажи!$L$2:$L$1000,$B$2,Продажи!$K$2:$K$1000,11) -> 0 | C15: =SUMIFS(Продажи!$J$2:$J$1000,Продажи!$L$2:$L$1000,$B$2,Продажи!$K$2:$K$1000,11) -> 0 | D15: =COUNTIFS(Продажи!$L$2:$L$1000,$B$2,Продажи!$K$2:$K$1000,11) -> 0 | E15: =IF(B15=0,0,C15/B15) -> 0
A16: Декабрь | B16: =SUMIFS(Продажи!$H$2:$H$1000,Продажи!$L$2:$L$1000,$B$2,Продажи!$K$2:$K$1000,12) -> 0 | C16: =SUMIFS(Продажи!$J$2:$J$1000,Продажи!$L$2:$L$1000,$B$2,Продажи!$K$2:$K$1000,12) -> 0 | D16: =COUNTIFS(Продажи!$L$2:$L$1000,$B$2,Продажи!$K$2:$K$1000,12) -> 0 | E16: =IF(B16=0,0,C16/B16) -> 0
A17: Итого | B17: =SUM(B5:B16) -> 870500 | C17: =SUM(C5:C16) -> 343500 | D17: =SUM(D5:D16) -> 8 | E17: =IF(B17=0,0,C17/B17) -> 0.3946008
A19: По товарам (за выбранный год) | G19: По клиентам (за выбранный год)
A20: Товар | B20: Продано, шт. | C20: Выручка | D20: Прибыль | E20: Место | G20: Клиент | H20: Позиций | I20: Выручка | J20: Место
A21: =IF(Товары!A2="","",Товары!B2) -> Товар 1 | B21: =IF(Товары!A2="","",SUMIFS(Продажи!$F$2:$F$1000,Продажи!$D$2:$D$1000,Товары!A2,Продажи!$L$2:$L$1000,$B$2)) -> 20 | C21: =IF(Товары!A2="","",SUMIFS(Продажи!$H$2:$H$1000,Продажи!$D$2:$D$1000,Товары!A2,Продажи!$L$2:$L$1000,$B$2)) -> 300000 | D21: =IF(Товары!A2="","",SUMIFS(Продажи!$J$2:$J$1000,Продажи!$D$2:$D$1000,Товары!A2,Продажи!$L$2:$L$1000,$B$2)) -> 120000 | E21: =IF(C21="","",RANK(C21,$C$21:$C$50)) -> 1 | G21: =IF(Клиенты!A2="","",Клиенты!A2) -> ТОО «Альфа» | H21: =IF(Клиенты!A2="","",COUNTIFS(Продажи!$C$2:$C$1000,Клиенты!A2,Продажи!$L$2:$L$1000,$B$2)) -> 3 | I21: =IF(Клиенты!A2="","",SUMIFS(Продажи!$H$2:$H$1000,Продажи!$C$2:$C$1000,Клиенты!A2,Продажи!$L$2:$L$1000,$B$2)) -> 260500 | J21: =IF(I21="","",RANK(I21,$I$21:$I$50)) -> 2
A22: =IF(Товары!A3="","",Товары!B3) -> Товар 2 | B22: =IF(Товары!A3="","",SUMIFS(Продажи!$F$2:$F$1000,Продажи!$D$2:$D$1000,Товары!A3,Продажи!$L$2:$L$1000,$B$2)) -> 13 | C22: =IF(Товары!A3="","",SUMIFS(Продажи!$H$2:$H$1000,Продажи!$D$2:$D$1000,Товары!A3,Продажи!$L$2:$L$1000,$B$2)) -> 110500 | D22: =IF(Товары!A3="","",SUMIFS(Продажи!$J$2:$J$1000,Продажи!$D$2:$D$1000,Товары!A3,Продажи!$L$2:$L$1000,$B$2)) -> 45500 | E22: =IF(C22="","",RANK(C22,$C$21:$C$50)) -> 4 | G22: =IF(Клиенты!A3="","",Клиенты!A3) -> ТОО «Бета» | H22: =IF(Клиенты!A3="","",COUNTIFS(Продажи!$C$2:$C$1000,Клиенты!A3,Продажи!$L$2:$L$1000,$B$2)) -> 2 | I22: =IF(Клиенты!A3="","",SUMIFS(Продажи!$H$2:$H$1000,Продажи!$C$2:$C$1000,Клиенты!A3,Продажи!$L$2:$L$1000,$B$2)) -> 156000 | J22: =IF(I22="","",RANK(I22,$I$21:$I$50)) -> 3
A23: =IF(Товары!A4="","",Товары!B4) -> Товар 3 | B23: =IF(Товары!A4="","",SUMIFS(Продажи!$F$2:$F$1000,Продажи!$D$2:$D$1000,Товары!A4,Продажи!$L$2:$L$1000,$B$2)) -> 50 | C23: =IF(Товары!A4="","",SUMIFS(Продажи!$H$2:$H$1000,Продажи!$D$2:$D$1000,Товары!A4,Продажи!$L$2:$L$1000,$B$2)) -> 160000 | D23: =IF(Товары!A4="","",SUMIFS(Продажи!$J$2:$J$1000,Продажи!$D$2:$D$1000,Товары!A4,Продажи!$L$2:$L$1000,$B$2)) -> 70000 | E23: =IF(C23="","",RANK(C23,$C$21:$C$50)) -> 3 | G23: =IF(Клиенты!A4="","",Клиенты!A4) -> ИП Нурланов | H23: =IF(Клиенты!A4="","",COUNTIFS(Продажи!$C$2:$C$1000,Клиенты!A4,Продажи!$L$2:$L$1000,$B$2)) -> 3 | I23: =IF(Клиенты!A4="","",SUMIFS(Продажи!$H$2:$H$1000,Продажи!$C$2:$C$1000,Клиенты!A4,Продажи!$L$2:$L$1000,$B$2)) -> 454000 | J23: =IF(I23="","",RANK(I23,$I$21:$I$50)) -> 1
A24: =IF(Товары!A5="","",Товары!B5) -> Товар 4 | B24: =IF(Товары!A5="","",SUMIFS(Продажи!$F$2:$F$1000,Продажи!$D$2:$D$1000,Товары!A5,Продажи!$L$2:$L$1000,$B$2)) -> 12 | C24: =IF(Товары!A5="","",SUMIFS(Продажи!$H$2:$H$1000,Продажи!$D$2:$D$1000,Товары!A5,Продажи!$L$2:$L$1000,$B$2)) -> 300000 | D24: =IF(Товары!A5="","",SUMIFS(Продажи!$J$2:$J$1000,Продажи!$D$2:$D$1000,Товары!A5,Продажи!$L$2:$L$1000,$B$2)) -> 108000 | E24: =IF(C24="","",RANK(C24,$C$21:$C$50)) -> 1 | G24: =IF(Клиенты!A5="","",Клиенты!A5) | H24: =IF(Клиенты!A5="","",COUNTIFS(Продажи!$C$2:$C$1000,Клиенты!A5,Продажи!$L$2:$L$1000,$B$2)) | I24: =IF(Клиенты!A5="","",SUMIFS(Продажи!$H$2:$H$1000,Продажи!$C$2:$C$1000,Клиенты!A5,Продажи!$L$2:$L$1000,$B$2)) | J24: =IF(I24="","",RANK(I24,$I$21:$I$50))
A25: =IF(Товары!A6="","",Товары!B6) | B25: =IF(Товары!A6="","",SUMIFS(Продажи!$F$2:$F$1000,Продажи!$D$2:$D$1000,Товары!A6,Продажи!$L$2:$L$1000,$B$2)) | C25: =IF(Товары!A6="","",SUMIFS(Продажи!$H$2:$H$1000,Продажи!$D$2:$D$1000,Товары!A6,Продажи!$L$2:$L$1000,$B$2)) | D25: =IF(Товары!A6="","",SUMIFS(Продажи!$J$2:$J$1000,Продажи!$D$2:$D$1000,Товары!A6,Продажи!$L$2:$L$1000,$B$2)) | E25: =IF(C25="","",RANK(C25,$C$21:$C$50)) | G25: =IF(Клиенты!A6="","",Клиенты!A6) | H25: =IF(Клиенты!A6="","",COUNTIFS(Продажи!$C$2:$C$1000,Клиенты!A6,Продажи!$L$2:$L$1000,$B$2)) | I25: =IF(Клиенты!A6="","",SUMIFS(Продажи!$H$2:$H$1000,Продажи!$C$2:$C$1000,Клиенты!A6,Продажи!$L$2:$L$1000,$B$2)) | J25: =IF(I25="","",RANK(I25,$I$21:$I$50))
A26: =IF(Товары!A7="","",Товары!B7) | B26: =IF(Товары!A7="","",SUMIFS(Продажи!$F$2:$F$1000,Продажи!$D$2:$D$1000,Товары!A7,Продажи!$L$2:$L$1000,$B$2)) | C26: =IF(Товары!A7="","",SUMIFS(Продажи!$H$2:$H$1000,Продажи!$D$2:$D$1000,Товары!A7,Продажи!$L$2:$L$1000,$B$2)) | D26: =IF(Товары!A7="","",SUMIFS(Продажи!$J$2:$J$1000,Продажи!$D$2:$D$1000,Товары!A7,Продажи!$L$2:$L$1000,$B$2)) | E26: =IF(C26="","",RANK(C26,$C$21:$C$50)) | G26: =IF(Клиенты!A7="","",Клиенты!A7) | H26: =IF(Клиенты!A7="","",COUNTIFS(Продажи!$C$2:$C$1000,Клиенты!A7,Продажи!$L$2:$L$1000,$B$2)) | I26: =IF(Клиенты!A7="","",SUMIFS(Продажи!$H$2:$H$1000,Продажи!$C$2:$C$1000,Клиенты!A7,Продажи!$L$2:$L$1000,$B$2)) | J26: =IF(I26="","",RANK(I26,$I$21:$I$50))
A27: =IF(Товары!A8="","",Товары!B8) | B27: =IF(Товары!A8="","",SUMIFS(Продажи!$F$2:$F$1000,Продажи!$D$2:$D$1000,Товары!A8,Продажи!$L$2:$L$1000,$B$2)) | C27: =IF(Товары!A8="","",SUMIFS(Продажи!$H$2:$H$1000,Продажи!$D$2:$D$1000,Товары!A8,Продажи!$L$2:$L$1000,$B$2)) | D27: =IF(Товары!A8="","",SUMIFS(Продажи!$J$2:$J$1000,Продажи!$D$2:$D$1000,Товары!A8,Продажи!$L$2:$L$1000,$B$2)) | E27: =IF(C27="","",RANK(C27,$C$21:$C$50)) | G27: =IF(Клиенты!A8="","",Клиенты!A8) | H27: =IF(Клиенты!A8="","",COUNTIFS(Продажи!$C$2:$C$1000,Клиенты!A8,Продажи!$L$2:$L$1000,$B$2)) | I27: =IF(Клиенты!A8="","",SUMIFS(Продажи!$H$2:$H$1000,Продажи!$C$2:$C$1000,Клиенты!A8,Продажи!$L$2:$L$1000,$B$2)) | J27: =IF(I27="","",RANK(I27,$I$21:$I$50))
A28: =IF(Товары!A9="","",Товары!B9) | B28: =IF(Товары!A9="","",SUMIFS(Продажи!$F$2:$F$1000,Продажи!$D$2:$D$1000,Товары!A9,Продажи!$L$2:$L$1000,$B$2)) | C28: =IF(Товары!A9="","",SUMIFS(Продажи!$H$2:$H$1000,Продажи!$D$2:$D$1000,Товары!A9,Продажи!$L$2:$L$1000,$B$2)) | D28: =IF(Товары!A9="","",SUMIFS(Продажи!$J$2:$J$1000,Продажи!$D$2:$D$1000,Товары!A9,Продажи!$L$2:$L$1000,$B$2)) | E28: =IF(C28="","",RANK(C28,$C$21:$C$50)) | G28: =IF(Клиенты!A9="","",Клиенты!A9) | H28: =IF(Клиенты!A9="","",COUNTIFS(Продажи!$C$2:$C$1000,Клиенты!A9,Продажи!$L$2:$L$1000,$B$2)) | I28: =IF(Клиенты!A9="","",SUMIFS(Продажи!$H$2:$H$1000,Продажи!$C$2:$C$1000,Клиенты!A9,Продажи!$L$2:$L$1000,$B$2)) | J28: =IF(I28="","",RANK(I28,$I$21:$I$50))
A29: =IF(Товары!A10="","",Товары!B10) | B29: =IF(Товары!A10="","",SUMIFS(Продажи!$F$2:$F$1000,Продажи!$D$2:$D$1000,Товары!A10,Продажи!$L$2:$L$1000,$B$2)) | C29: =IF(Товары!A10="","",SUMIFS(Продажи!$H$2:$H$1000,Продажи!$D$2:$D$1000,Товары!A10,Продажи!$L$2:$L$1000,$B$2)) | D29: =IF(Товары!A10="","",SUMIFS(Продажи!$J$2:$J$1000,Продажи!$D$2:$D$1000,Товары!A10,Продажи!$L$2:$L$1000,$B$2)) | E29: =IF(C29="","",RANK(C29,$C$21:$C$50)) | G29: =IF(Клиенты!A10="","",Клиенты!A10) | H29: =IF(Клиенты!A10="","",COUNTIFS(Продажи!$C$2:$C$1000,Клиенты!A10,Продажи!$L$2:$L$1000,$B$2)) | I29: =IF(Клиенты!A10="","",SUMIFS(Продажи!$H$2:$H$1000,Продажи!$C$2:$C$1000,Клиенты!A10,Продажи!$L$2:$L$1000,$B$2)) | J29: =IF(I29="","",RANK(I29,$I$21:$I$50))
A30: =IF(Товары!A11="","",Товары!B11) | B30: =IF(Товары!A11="","",SUMIFS(Продажи!$F$2:$F$1000,Продажи!$D$2:$D$1000,Товары!A11,Продажи!$L$2:$L$1000,$B$2)) | C30: =IF(Товары!A11="","",SUMIFS(Продажи!$H$2:$H$1000,Продажи!$D$2:$D$1000,Товары!A11,Продажи!$L$2:$L$1000,$B$2)) | D30: =IF(Товары!A11="","",SUMIFS(Продажи!$J$2:$J$1000,Продажи!$D$2:$D$1000,Товары!A11,Продажи!$L$2:$L$1000,$B$2)) | E30: =IF(C30="","",RANK(C30,$C$21:$C$50)) | G30: =IF(Клиенты!A11="","",Клиенты!A11) | H30: =IF(Клиенты!A11="","",COUNTIFS(Продажи!$C$2:$C$1000,Клиенты!A11,Продажи!$L$2:$L$1000,$B$2)) | I30: =IF(Клиенты!A11="","",SUMIFS(Продажи!$H$2:$H$1000,Продажи!$C$2:$C$1000,Клиенты!A11,Продажи!$L$2:$L$1000,$B$2)) | J30: =IF(I30="","",RANK(I30,$I$21:$I$50))
A31: =IF(Товары!A12="","",Товары!B12) | B31: =IF(Товары!A12="","",SUMIFS(Продажи!$F$2:$F$1000,Продажи!$D$2:$D$1000,Товары!A12,Продажи!$L$2:$L$1000,$B$2)) | C31: =IF(Товары!A12="","",SUMIFS(Продажи!$H$2:$H$1000,Продажи!$D$2:$D$1000,Товары!A12,Продажи!$L$2:$L$1000,$B$2)) | D31: =IF(Товары!A12="","",SUMIFS(Продажи!$J$2:$J$1000,Продажи!$D$2:$D$1000,Товары!A12,Продажи!$L$2:$L$1000,$B$2)) | E31: =IF(C31="","",RANK(C31,$C$21:$C$50)) | G31: =IF(Клиенты!A12="","",Клиенты!A12) | H31: =IF(Клиенты!A12="","",COUNTIFS(Продажи!$C$2:$C$1000,Клиенты!A12,Продажи!$L$2:$L$1000,$B$2)) | I31: =IF(Клиенты!A12="","",SUMIFS(Продажи!$H$2:$H$1000,Продажи!$C$2:$C$1000,Клиенты!A12,Продажи!$L$2:$L$1000,$B$2)) | J31: =IF(I31="","",RANK(I31,$I$21:$I$50))
A32: =IF(Товары!A13="","",Товары!B13) | B32: =IF(Товары!A13="","",SUMIFS(Продажи!$F$2:$F$1000,Продажи!$D$2:$D$1000,Товары!A13,Продажи!$L$2:$L$1000,$B$2)) | C32: =IF(Товары!A13="","",SUMIFS(Продажи!$H$2:$H$1000,Продажи!$D$2:$D$1000,Товары!A13,Продажи!$L$2:$L$1000,$B$2)) | D32: =IF(Товары!A13="","",SUMIFS(Продажи!$J$2:$J$1000,Продажи!$D$2:$D$1000,Товары!A13,Продажи!$L$2:$L$1000,$B$2)) | E32: =IF(C32="","",RANK(C32,$C$21:$C$50)) | G32: =IF(Клиенты!A13="","",Клиенты!A13) | H32: =IF(Клиенты!A13="","",COUNTIFS(Продажи!$C$2:$C$1000,Клиенты!A13,Продажи!$L$2:$L$1000,$B$2)) | I32: =IF(Клиенты!A13="","",SUMIFS(Продажи!$H$2:$H$1000,Продажи!$C$2:$C$1000,Клиенты!A13,Продажи!$L$2:$L$1000,$B$2)) | J32: =IF(I32="","",RANK(I32,$I$21:$I$50))
... A50: =IF(Товары!A31="","",Товары!B31) | B50: =IF(Товары!A31="","",SUMIFS(Продажи!$F$2:$F$1000,Продажи!$D$2:$D$1000,Товары!A31,Продажи!$L$2:$L$1000,$B$2)) | C50: =IF(Товары!A31="","",SUMIFS(Продажи!$H$2:$H$1000,Продажи!$D$2:$D$1000,Товары!A31,Продажи!$L$2:$L$1000,$B$2)) | D50: =IF(Товары!A31="","",SUMIFS(Продажи!$J$2:$J$1000,Продажи!$D$2:$D$1000,Товары!A31,Продажи!$L$2:$L$1000,$B$2)) | E50: =IF(C50="","",RANK(C50,$C$21:$C$50)) | G50: =IF(Клиенты!A31="","",Клиенты!A31) | H50: =IF(Клиенты!A31="","",COUNTIFS(Продажи!$C$2:$C$1000,Клиенты!A31,Продажи!$L$2:$L$1000,$B$2)) | I50: =IF(Клиенты!A31="","",SUMIFS(Продажи!$H$2:$H$1000,Продажи!$C$2:$C$1000,Клиенты!A31,Продажи!$L$2:$L$1000,$B$2)) | J50: =IF(I50="","",RANK(I50,$I$21:$I$50))

Sheet Счет
A1: СЧЁТ НА ОПЛАТУ
A3: Номер счёта: | B3: 1001 | C3: ← введите номер счёта из листа «Продажи»
A4: Дата: | B4: =IFERROR(INDEX(Продажи!$A$2:$A$1000,MATCH($B$3&"|1",Продажи!$M$2:$M$1000,0)),"") -> 46034
A5: Клиент: | B5: =IFERROR(INDEX(Продажи!$C$2:$C$1000,MATCH($B$3&"|1",Продажи!$M$2:$M$1000,0)),"счёт не найден") -> ТОО «Альфа»
A6: Реквизиты клиента: | B6: =IFERROR(INDEX(Клиенты!$D$2:$D$200,MATCH(B5,Клиенты!$A$2:$A$200,0)),"") -> г. Астана, ул. Примерная 1, БИН 000000000001
A7: Поставщик: | B7: ТОО «Ваша компания», БИН ..., адрес ..., IBAN ...
A9: № | B9: Наименование | C9: Кол-во | D9: Цена | E9: Сумма
A10: =IF(ISNUMBER(MATCH($B$3&"|"&1,Продажи!$M$2:$M$1000,0)),1,"") -> 1 | B10: =IF($A10="","",INDEX(Продажи!$E$2:$E$1000,MATCH($B$3&"|"&$A10,Продажи!$M$2:$M$1000,0))) -> Товар 1 | C10: =IF($A10="","",INDEX(Продажи!$F$2:$F$1000,MATCH($B$3&"|"&$A10,Продажи!$M$2:$M$1000,0))) -> 10 | D10: =IF($A10="","",INDEX(Продажи!$G$2:$G$1000,MATCH($B$3&"|"&$A10,Продажи!$M$2:$M$1000,0))) -> 15000 | E10: =IF($A10="","",INDEX(Продажи!$H$2:$H$1000,MATCH($B$3&"|"&$A10,Продажи!$M$2:$M$1000,0))) -> 150000
A11: =IF(ISNUMBER(MATCH($B$3&"|"&2,Продажи!$M$2:$M$1000,0)),2,"") -> 2 | B11: =IF($A11="","",INDEX(Продажи!$E$2:$E$1000,MATCH($B$3&"|"&$A11,Продажи!$M$2:$M$1000,0))) -> Товар 2 | C11: =IF($A11="","",INDEX(Продажи!$F$2:$F$1000,MATCH($B$3&"|"&$A11,Продажи!$M$2:$M$1000,0))) -> 5 | D11: =IF($A11="","",INDEX(Продажи!$G$2:$G$1000,MATCH($B$3&"|"&$A11,Продажи!$M$2:$M$1000,0))) -> 8500 | E11: =IF($A11="","",INDEX(Продажи!$H$2:$H$1000,MATCH($B$3&"|"&$A11,Продажи!$M$2:$M$1000,0))) -> 42500
A12: =IF(ISNUMBER(MATCH($B$3&"|"&3,Продажи!$M$2:$M$1000,0)),3,"") | B12: =IF($A12="","",INDEX(Продажи!$E$2:$E$1000,MATCH($B$3&"|"&$A12,Продажи!$M$2:$M$1000,0))) | C12: =IF($A12="","",INDEX(Продажи!$F$2:$F$1000,MATCH($B$3&"|"&$A12,Продажи!$M$2:$M$1000,0))) | D12: =IF($A12="","",INDEX(Продажи!$G$2:$G$1000,MATCH($B$3&"|"&$A12,Продажи!$M$2:$M$1000,0))) | E12: =IF($A12="","",INDEX(Продажи!$H$2:$H$1000,MATCH($B$3&"|"&$A12,Продажи!$M$2:$M$1000,0)))
A13: =IF(ISNUMBER(MATCH($B$3&"|"&4,Продажи!$M$2:$M$1000,0)),4,"") | B13: =IF($A13="","",INDEX(Продажи!$E$2:$E$1000,MATCH($B$3&"|"&$A13,Продажи!$M$2:$M$1000,0))) | C13: =IF($A13="","",INDEX(Продажи!$F$2:$F$1000,MATCH($B$3&"|"&$A13,Продажи!$M$2:$M$1000,0))) | D13: =IF($A13="","",INDEX(Продажи!$G$2:$G$1000,MATCH($B$3&"|"&$A13,Продажи!$M$2:$M$1000,0))) | E13: =IF($A13="","",INDEX(Продажи!$H$2:$H$1000,MATCH($B$3&"|"&$A13,Продажи!$M$2:$M$1000,0)))
A14: =IF(ISNUMBER(MATCH($B$3&"|"&5,Продажи!$M$2:$M$1000,0)),5,"") | B14: =IF($A14="","",INDEX(Продажи!$E$2:$E$1000,MATCH($B$3&"|"&$A14,Продажи!$M$2:$M$1000,0))) | C14: =IF($A14="","",INDEX(Продажи!$F$2:$F$1000,MATCH($B$3&"|"&$A14,Продажи!$M$2:$M$1000,0))) | D14: =IF($A14="","",INDEX(Продажи!$G$2:$G$1000,MATCH($B$3&"|"&$A14,Продажи!$M$2:$M$1000,0))) | E14: =IF($A14="","",INDEX(Продажи!$H$2:$H$1000,MATCH($B$3&"|"&$A14,Продажи!$M$2:$M$1000,0)))
A15: =IF(ISNUMBER(MATCH($B$3&"|"&6,Продажи!$M$2:$M$1000,0)),6,"") | B15: =IF($A15="","",INDEX(Продажи!$E$2:$E$1000,MATCH($B$3&"|"&$A15,Продажи!$M$2:$M$1000,0))) | C15: =IF($A15="","",INDEX(Продажи!$F$2:$F$1000,MATCH($B$3&"|"&$A15,Продажи!$M$2:$M$1000,0))) | D15: =IF($A15="","",INDEX(Продажи!$G$2:$G$1000,MATCH($B$3&"|"&$A15,Продажи!$M$2:$M$1000,0))) | E15: =IF($A15="","",INDEX(Продажи!$H$2:$H$1000,MATCH($B$3&"|"&$A15,Продажи!$M$2:$M$1000,0)))
A16: =IF(ISNUMBER(MATCH($B$3&"|"&7,Продажи!$M$2:$M$1000,0)),7,"") | B16: =IF($A16="","",INDEX(Продажи!$E$2:$E$1000,MATCH($B$3&"|"&$A16,Продажи!$M$2:$M$1000,0))) | C16: =IF($A16="","",INDEX(Продажи!$F$2:$F$1000,MATCH($B$3&"|"&$A16,Продажи!$M$2:$M$1000,0))) | D16: =IF($A16="","",INDEX(Продажи!$G$2:$G$1000,MATCH($B$3&"|"&$A16,Продажи!$M$2:$M$1000,0))) | E16: =IF($A16="","",INDEX(Продажи!$H$2:$H$1000,MATCH($B$3&"|"&$A16,Продажи!$M$2:$M$1000,0)))
A17: =IF(ISNUMBER(MATCH($B$3&"|"&8,Продажи!$M$2:$M$1000,0)),8,"") | B17: =IF($A17="","",INDEX(Продажи!$E$2:$E$1000,MATCH($B$3&"|"&$A17,Продажи!$M$2:$M$1000,0))) | C17: =IF($A17="","",INDEX(Продажи!$F$2:$F$1000,MATCH($B$3&"|"&$A17,Продажи!$M$2:$M$1000,0))) | D17: =IF($A17="","",INDEX(Продажи!$G$2:$G$1000,MATCH($B$3&"|"&$A17,Продажи!$M$2:$M$1000,0))) | E17: =IF($A17="","",INDEX(Продажи!$H$2:$H$1000,MATCH($B$3&"|"&$A17,Продажи!$M$2:$M$1000,0)))
A18: =IF(ISNUMBER(MATCH($B$3&"|"&9,Продажи!$M$2:$M$1000,0)),9,"") | B18: =IF($A18="","",INDEX(Продажи!$E$2:$E$1000,MATCH($B$3&"|"&$A18,Продажи!$M$2:$M$1000,0))) | C18: =IF($A18="","",INDEX(Продажи!$F$2:$F$1000,MATCH($B$3&"|"&$A18,Продажи!$M$2:$M$1000,0))) | D18: =IF($A18="","",INDEX(Продажи!$G$2:$G$1000,MATCH($B$3&"|"&$A18,Продажи!$M$2:$M$1000,0))) | E18: =IF($A18="","",INDEX(Продажи!$H$2:$H$1000,MATCH($B$3&"|"&$A18,Продажи!$M$2:$M$1000,0)))
A19: =IF(ISNUMBER(MATCH($B$3&"|"&10,Продажи!$M$2:$M$1000,0)),10,"") | B19: =IF($A19="","",INDEX(Продажи!$E$2:$E$1000,MATCH($B$3&"|"&$A19,Продажи!$M$2:$M$1000,0))) | C19: =IF($A19="","",INDEX(Продажи!$F$2:$F$1000,MATCH($B$3&"|"&$A19,Продажи!$M$2:$M$1000,0))) | D19: =IF($A19="","",INDEX(Продажи!$G$2:$G$1000,MATCH($B$3&"|"&$A19,Продажи!$M$2:$M$1000,0))) | E19: =IF($A19="","",INDEX(Продажи!$H$2:$H$1000,MATCH($B$3&"|"&$A19,Продажи!$M$2:$M$1000,0)))
A20: =IF(ISNUMBER(MATCH($B$3&"|"&11,Продажи!$M$2:$M$1000,0)),11,"") | B20: =IF($A20="","",INDEX(Продажи!$E$2:$E$1000,MATCH($B$3&"|"&$A20,Продажи!$M$2:$M$1000,0))) | C20: =IF($A20="","",INDEX(Продажи!$F$2:$F$1000,MATCH($B$3&"|"&$A20,Продажи!$M$2:$M$1000,0))) | D20: =IF($A20="","",INDEX(Продажи!$G$2:$G$1000,MATCH($B$3&"|"&$A20,Продажи!$M$2:$M$1000,0))) | E20: =IF($A20="","",INDEX(Продажи!$H$2:$H$1000,MATCH($B$3&"|"&$A20,Продажи!$M$2:$M$1000,0)))
A21: =IF(ISNUMBER(MATCH($B$3&"|"&12,Продажи!$M$2:$M$1000,0)),12,"") | B21: =IF($A21="","",INDEX(Продажи!$E$2:$E$1000,MATCH($B$3&"|"&$A21,Продажи!$M$2:$M$1000,0))) | C21: =IF($A21="","",INDEX(Продажи!$F$2:$F$1000,MATCH($B$3&"|"&$A21,Продажи!$M$2:$M$1000,0))) | D21: =IF($A21="","",INDEX(Продажи!$G$2:$G$1000,MATCH($B$3&"|"&$A21,Продажи!$M$2:$M$1000,0))) | E21: =IF($A21="","",INDEX(Продажи!$H$2:$H$1000,MATCH($B$3&"|"&$A21,Продажи!$M$2:$M$1000,0)))
A22: =IF(ISNUMBER(MATCH($B$3&"|"&13,Продажи!$M$2:$M$1000,0)),13,"") | B22: =IF($A22="","",INDEX(Продажи!$E$2:$E$1000,MATCH($B$3&"|"&$A22,Продажи!$M$2:$M$1000,0))) | C22: =IF($A22="","",INDEX(Продажи!$F$2:$F$1000,MATCH($B$3&"|"&$A22,Продажи!$M$2:$M$1000,0))) | D22: =IF($A22="","",INDEX(Продажи!$G$2:$G$1000,MATCH($B$3&"|"&$A22,Продажи!$M$2:$M$1000,0))) | E22: =IF($A22="","",INDEX(Продажи!$H$2:$H$1000,MATCH($B$3&"|"&$A22,Продажи!$M$2:$M$1000,0)))
A23: =IF(ISNUMBER(MATCH($B$3&"|"&14,Продажи!$M$2:$M$1000,0)),14,"") | B23: =IF($A23="","",INDEX(Продажи!$E$2:$E$1000,MATCH($B$3&"|"&$A23,Продажи!$M$2:$M$1000,0))) | C23: =IF($A23="","",INDEX(Продажи!$F$2:$F$1000,MATCH($B$3&"|"&$A23,Продажи!$M$2:$M$1000,0))) | D23: =IF($A23="","",INDEX(Продажи!$G$2:$G$1000,MATCH($B$3&"|"&$A23,Продажи!$M$2:$M$1000,0))) | E23: =IF($A23="","",INDEX(Продажи!$H$2:$H$1000,MATCH($B$3&"|"&$A23,Продажи!$M$2:$M$1000,0)))
A24: =IF(ISNUMBER(MATCH($B$3&"|"&15,Продажи!$M$2:$M$1000,0)),15,"") | B24: =IF($A24="","",INDEX(Продажи!$E$2:$E$1000,MATCH($B$3&"|"&$A24,Продажи!$M$2:$M$1000,0))) | C24: =IF($A24="","",INDEX(Продажи!$F$2:$F$1000,MATCH($B$3&"|"&$A24,Продажи!$M$2:$M$1000,0))) | D24: =IF($A24="","",INDEX(Продажи!$G$2:$G$1000,MATCH($B$3&"|"&$A24,Продажи!$M$2:$M$1000,0))) | E24: =IF($A24="","",INDEX(Продажи!$H$2:$H$1000,MATCH($B$3&"|"&$A24,Продажи!$M$2:$M$1000,0)))
A25: =IF(ISNUMBER(MATCH($B$3&"|"&16,Продажи!$M$2:$M$1000,0)),16,"") | B25: =IF($A25="","",INDEX(Продажи!$E$2:$E$1000,MATCH($B$3&"|"&$A25,Продажи!$M$2:$M$1000,0))) | C25: =IF($A25="","",INDEX(Продажи!$F$2:$F$1000,MATCH($B$3&"|"&$A25,Продажи!$M$2:$M$1000,0))) | D25: =IF($A25="","",INDEX(Продажи!$G$2:$G$1000,MATCH($B$3&"|"&$A25,Продажи!$M$2:$M$1000,0))) | E25: =IF($A25="","",INDEX(Продажи!$H$2:$H$1000,MATCH($B$3&"|"&$A25,Продажи!$M$2:$M$1000,0)))
A26: =IF(ISNUMBER(MATCH($B$3&"|"&17,Продажи!$M$2:$M$1000,0)),17,"") | B26: =IF($A26="","",INDEX(Продажи!$E$2:$E$1000,MATCH($B$3&"|"&$A26,Продажи!$M$2:$M$1000,0))) | C26: =IF($A26="","",INDEX(Продажи!$F$2:$F$1000,MATCH($B$3&"|"&$A26,Продажи!$M$2:$M$1000,0))) | D26: =IF($A26="","",INDEX(Продажи!$G$2:$G$1000,MATCH($B$3&"|"&$A26,Продажи!$M$2:$M$1000,0))) | E26: =IF($A26="","",INDEX(Продажи!$H$2:$H$1000,MATCH($B$3&"|"&$A26,Продажи!$M$2:$M$1000,0)))
A27: =IF(ISNUMBER(MATCH($B$3&"|"&18,Продажи!$M$2:$M$1000,0)),18,"") | B27: =IF($A27="","",INDEX(Продажи!$E$2:$E$1000,MATCH($B$3&"|"&$A27,Продажи!$M$2:$M$1000,0))) | C27: =IF($A27="","",INDEX(Продажи!$F$2:$F$1000,MATCH($B$3&"|"&$A27,Продажи!$M$2:$M$1000,0))) | D27: =IF($A27="","",INDEX(Продажи!$G$2:$G$1000,MATCH($B$3&"|"&$A27,Продажи!$M$2:$M$1000,0))) | E27: =IF($A27="","",INDEX(Продажи!$H$2:$H$1000,MATCH($B$3&"|"&$A27,Продажи!$M$2:$M$1000,0)))
A28: =IF(ISNUMBER(MATCH($B$3&"|"&19,Продажи!$M$2:$M$1000,0)),19,"") | B28: =IF($A28="","",INDEX(Продажи!$E$2:$E$1000,MATCH($B$3&"|"&$A28,Продажи!$M$2:$M$1000,0))) | C28: =IF($A28="","",INDEX(Продажи!$F$2:$F$1000,MATCH($B$3&"|"&$A28,Продажи!$M$2:$M$1000,0))) | D28: =IF($A28="","",INDEX(Продажи!$G$2:$G$1000,MATCH($B$3&"|"&$A28,Продажи!$M$2:$M$1000,0))) | E28: =IF($A28="","",INDEX(Продажи!$H$2:$H$1000,MATCH($B$3&"|"&$A28,Продажи!$M$2:$M$1000,0)))
A29: =IF(ISNUMBER(MATCH($B$3&"|"&20,Продажи!$M$2:$M$1000,0)),20,"") | B29: =IF($A29="","",INDEX(Продажи!$E$2:$E$1000,MATCH($B$3&"|"&$A29,Продажи!$M$2:$M$1000,0))) | C29: =IF($A29="","",INDEX(Продажи!$F$2:$F$1000,MATCH($B$3&"|"&$A29,Продажи!$M$2:$M$1000,0))) | D29: =IF($A29="","",INDEX(Продажи!$G$2:$G$1000,MATCH($B$3&"|"&$A29,Продажи!$M$2:$M$1000,0))) | E29: =IF($A29="","",INDEX(Продажи!$H$2:$H$1000,MATCH($B$3&"|"&$A29,Продажи!$M$2:$M$1000,0)))
D30: ИТОГО: | E30: =SUM(E10:E29) -> 192500
